{
  "videos": [
    {
      "title": "Deep Sea Creatures Ep. 46 \u2014 Gulper Eel | Deep Sea Finder",
      "video_id": "S_OKpvhNDJc",
      "url": "https://youtu.be/S_OKpvhNDJc",
      "embed": "https://www.youtube.com/embed/S_OKpvhNDJc",
      "date": "2026-05-07",
      "thumbnail": "https://img.youtube.com/vi/S_OKpvhNDJc/maxresdefault.jpg"
    },
    {
      "title": "Deep Sea Creatures Ep. 45 \u2014 Crown Of Thorns Starfish | Deep Sea Finder",
      "video_id": "SjtoDB1rp8w",
      "url": "https://youtu.be/SjtoDB1rp8w",
      "embed": "https://www.youtube.com/embed/SjtoDB1rp8w",
      "date": "2026-05-06",
      "thumbnail": "https://img.youtube.com/vi/SjtoDB1rp8w/maxresdefault.jpg"
    },
    {
      "title": "Deep Sea Creatures Ep. 44 \u2014 Flying Gurnard | Deep Sea Finder",
      "video_id": "6SLtZ56iElM",
      "url": "https://youtu.be/6SLtZ56iElM",
      "embed": "https://www.youtube.com/embed/6SLtZ56iElM",
      "date": "2026-05-05",
      "thumbnail": "https://img.youtube.com/vi/6SLtZ56iElM/maxresdefault.jpg"
    },
    {
      "title": "Deep Sea Creatures Ep. 43 \u2014 Sea Nettle Jellyfish | Deep Sea Finder",
      "video_id": "xER8SNqpIyQ",
      "url": "https://youtu.be/xER8SNqpIyQ",
      "embed": "https://www.youtube.com/embed/xER8SNqpIyQ",
      "date": "2026-05-05",
      "thumbnail": "https://img.youtube.com/vi/xER8SNqpIyQ/maxresdefault.jpg"
    },
    {
      "title": "Deep Sea Creatures Ep. 41 \u2014 Feather Star | Deep Sea Finder",
      "video_id": "N1Ld31sUzf8",
      "url": "https://youtu.be/N1Ld31sUzf8",
      "embed": "https://www.youtube.com/embed/N1Ld31sUzf8",
      "date": "2026-04-30",
      "thumbnail": "https://img.youtube.com/vi/N1Ld31sUzf8/maxresdefault.jpg"
    },
    {
      "title": "Deep Sea Creatures Ep. 40 \u2014 Great White Shark | Deep Sea Finder",
      "video_id": "hTJAU_xxy50",
      "url": "https://youtu.be/hTJAU_xxy50",
      "embed": "https://www.youtube.com/embed/hTJAU_xxy50",
      "date": "2026-04-28",
      "thumbnail": "https://img.youtube.com/vi/hTJAU_xxy50/maxresdefault.jpg"
    },
    {
      "title": "Deep Sea Creatures Ep. 39 \u2014 Great White Shark | Deep Sea Finder",
      "video_id": "5c_gbcWfduk",
      "url": "https://youtu.be/5c_gbcWfduk",
      "embed": "https://www.youtube.com/embed/5c_gbcWfduk",
      "date": "2026-04-28",
      "thumbnail": "https://img.youtube.com/vi/5c_gbcWfduk/maxresdefault.jpg"
    },
    {
      "title": "Deep Sea Creatures Ep. 38 \u2014 Orca | Deep Sea Finder",
      "video_id": "xVhXMvZVEi8",
      "url": "https://youtu.be/xVhXMvZVEi8",
      "embed": "https://www.youtube.com/embed/xVhXMvZVEi8",
      "date": "2026-04-27",
      "thumbnail": "https://img.youtube.com/vi/xVhXMvZVEi8/maxresdefault.jpg"
    },
    {
      "title": "Deep Sea Creatures Ep. 37 \u2014 Stoplight Loosejaw | Deep Sea Finder",
      "video_id": "38v4cdMv3rM",
      "url": "https://youtu.be/38v4cdMv3rM",
      "embed": "https://www.youtube.com/embed/38v4cdMv3rM",
      "date": "2026-04-27",
      "thumbnail": "https://img.youtube.com/vi/38v4cdMv3rM/maxresdefault.jpg"
    },
    {
      "title": "Deep Sea Creatures Ep. 36 \u2014 Leafy Scorpionfish | Deep Sea Finder",
      "video_id": "6lWuEGJarJI",
      "url": "https://youtu.be/6lWuEGJarJI",
      "embed": "https://www.youtube.com/embed/6lWuEGJarJI",
      "date": "2026-04-26",
      "thumbnail": "https://img.youtube.com/vi/6lWuEGJarJI/maxresdefault.jpg"
    },
    {
      "title": "Deep Sea Creatures Ep. 35 \u2014 Dragonfish | Deep Sea Finder",
      "video_id": "0de2dtCmNok",
      "url": "https://youtu.be/0de2dtCmNok",
      "embed": "https://www.youtube.com/embed/0de2dtCmNok",
      "date": "2026-04-25",
      "thumbnail": "https://img.youtube.com/vi/0de2dtCmNok/maxresdefault.jpg"
    },
    {
      "title": "Deep Sea Creatures Ep. 34 \u2014 Ribbon Eel | Deep Sea Finder",
      "video_id": "GcZ-C9h7S14",
      "url": "https://youtu.be/GcZ-C9h7S14",
      "embed": "https://www.youtube.com/embed/GcZ-C9h7S14",
      "date": "2026-04-25",
      "thumbnail": "https://img.youtube.com/vi/GcZ-C9h7S14/maxresdefault.jpg"
    },
    {
      "title": "Deep Sea Creatures Ep. 33 \u2014 Giant Squid | Deep Sea Finder",
      "video_id": "A6g1unknvBQ",
      "url": "https://youtu.be/A6g1unknvBQ",
      "embed": "https://www.youtube.com/embed/A6g1unknvBQ",
      "date": "2026-04-23",
      "thumbnail": "https://img.youtube.com/vi/A6g1unknvBQ/maxresdefault.jpg"
    },
    {
      "title": "Deep Sea Creatures Ep. 32 \u2014 Giant Squid | Deep Sea Finder",
      "video_id": "pAaNCC1we3I",
      "url": "https://youtu.be/pAaNCC1we3I",
      "embed": "https://www.youtube.com/embed/pAaNCC1we3I",
      "date": "2026-04-23",
      "thumbnail": "https://img.youtube.com/vi/pAaNCC1we3I/maxresdefault.jpg"
    },
    {
      "title": "Deep Sea Creatures Ep. 31 \u2014 Black Swallower | Deep Sea Finder",
      "video_id": "2rUTX2IEKeY",
      "url": "https://youtu.be/2rUTX2IEKeY",
      "embed": "https://www.youtube.com/embed/2rUTX2IEKeY",
      "date": "2026-04-22",
      "thumbnail": "https://img.youtube.com/vi/2rUTX2IEKeY/maxresdefault.jpg"
    },
    {
      "title": "Deep Sea Creatures Ep. 30 \u2014 Immortal Jellyfish | Deep Sea Finder",
      "video_id": "ANizku6DT5s",
      "url": "https://youtu.be/ANizku6DT5s",
      "embed": "https://www.youtube.com/embed/ANizku6DT5s",
      "date": "2026-04-21",
      "thumbnail": "https://img.youtube.com/vi/ANizku6DT5s/maxresdefault.jpg"
    },
    {
      "title": "Deep Sea Creatures Ep. 29 \u2014 Humpback Whale | Deep Sea Finder",
      "video_id": "tlQSN4OuZ3M",
      "url": "https://youtu.be/tlQSN4OuZ3M",
      "embed": "https://www.youtube.com/embed/tlQSN4OuZ3M",
      "date": "2026-04-21",
      "thumbnail": "https://img.youtube.com/vi/tlQSN4OuZ3M/maxresdefault.jpg"
    },
    {
      "title": "Deep Sea Creatures Ep. 33 \u2014 Leafy Sea Dragon | Deep Sea Finder",
      "video_id": "6WuI2xNOIGU",
      "url": "https://youtu.be/6WuI2xNOIGU",
      "embed": "https://www.youtube.com/embed/6WuI2xNOIGU",
      "date": "2026-04-21",
      "thumbnail": "https://img.youtube.com/vi/6WuI2xNOIGU/maxresdefault.jpg"
    },
    {
      "title": "Deep Sea Creatures Ep. 32 \u2014 Boxfish | Deep Sea Finder",
      "video_id": "GwhbD_AjhyQ",
      "url": "https://youtu.be/GwhbD_AjhyQ",
      "embed": "https://www.youtube.com/embed/GwhbD_AjhyQ",
      "date": "2026-04-21",
      "thumbnail": "https://img.youtube.com/vi/GwhbD_AjhyQ/maxresdefault.jpg"
    },
    {
      "title": "Deep Sea Creatures Ep. 31 \u2014 Whale Fall Ecosystem | Deep Sea Finder",
      "video_id": "qYVqpFNvs30",
      "url": "https://youtu.be/qYVqpFNvs30",
      "embed": "https://www.youtube.com/embed/qYVqpFNvs30",
      "date": "2026-04-20",
      "thumbnail": "https://img.youtube.com/vi/qYVqpFNvs30/maxresdefault.jpg"
    }
  ]
}